sommify/__init__.py
sommify/regex.py
sommify/test.py
sommify/utils.py
sommify/countries/__init__.py
sommify/data/__init__.py
sommify/data/categories.py
sommify/data/constants.py
sommify/data/cuisine.py
sommify/data/embeddings.py
sommify/data/ingredient_funnel.py
sommify/data/ingredients.py
sommify/data/mean_ing_embedding_per_tag.csv
sommify/data/meat.py
sommify/data/modifiers.py
sommify/data/vegetables.py
sommify/data/vulgar_fractions.py
sommify/data/ingredient_categories/__init__.py
sommify/data/ingredient_categories/cheeses.py
sommify/data/ingredient_categories/drinks.py
sommify/data/ingredient_categories/fruit.py
sommify/data/ingredient_categories/herbs.py
sommify/data/ingredient_categories/legumes.py
sommify/data/ingredient_categories/meats.py
sommify/data/ingredient_categories/nuts.py
sommify/data/ingredient_categories/pasta.py
sommify/data/ingredient_categories/spices.py
sommify/data/ingredient_categories/vegetables.py
sommify/nn/__init__.py
sommify/nn/model.py
sommify/nn/recipe.py
sommify/nn/wine.py
sommify/nn/config/cooking_techniques.json
sommify/nn/config/cooking_utensils.json
sommify/nn/config/recipe_config.yaml
sommify/nn/config/wine_config.yaml
sommify/pairing/__init__.py
sommify/pairing/example.py
sommify/pairing/hash.py
sommify/pairing/scorers.py
sommify/pairing/selection.py
sommify/pairing/signals.py
sommify/pairing/similarity.py
sommify/pairing/utils.py
sommify/prompts/__init__.py
sommify/prompts/data/__init__.py
sommify/prompts/data/default.py
sommify/pygrape/__init__.py
sommify/pygrape/data.py
sommify/pynotesandhints/__init__.py
sommify/pynotesandhints/data.py
sommify/pyregion/__init__.py
sommify/pyregion/data.py
sommify/recipes/__init__.py
sommify/recipes/elastic.py
sommify/recipes/reader.py
sommify/tests/__init__.py
sommify/tests/test_bipolar_signals.py
sommify/tests/test_elastic.py
sommify/tests/test_pairing.py
sommify/tests/test_prompts.py
sommify/tests/test_pygrape.py
sommify/tests/test_pyregion.py
sommify/tests/test_recipe_reader.py
sommify-0.10.12.dist-info/METADATA
sommify-0.10.12.dist-info/WHEEL
sommify-0.10.12.dist-info/licenses/LICENSE
sommify-0.10.12.dist-info/RECORD
